blueprint/__init__.py
blueprint/cli.py
blueprint/templates/README_template.md
blueprint/templates/environment.yml
blueprint/templates/gitignore_template.txt
blueprint/templates/logger.yml
ds_blueprint-0.1.0.dist-info/METADATA
ds_blueprint-0.1.0.dist-info/WHEEL
ds_blueprint-0.1.0.dist-info/entry_points.txt
ds_blueprint-0.1.0.dist-info/RECORD
